threat_weaver/__init__.py
threat_weaver/reader.py
threat_weaver/call/__init__.py
threat_weaver/call/indexes.py
threat_weaver/call/pattern.py
threat_weaver/core/__init__.py
threat_weaver/core/analyze.py
threat_weaver/core/graph.py
threat_weaver/kb/interaction.yaml
threat_weaver-0.7.14.dist-info/licenses/LICENSE
threat_weaver-0.7.14.dist-info/METADATA
threat_weaver-0.7.14.dist-info/WHEEL
threat_weaver-0.7.14.dist-info/top_level.txt
threat_weaver-0.7.14.dist-info/RECORD
