Metadata-Version: 2.4
Name: threat-weaver
Version: 0.7.14
Summary: A Dynamic Attack Graph Generation Approach
Author-email: gaochengliang <chengliang_gao@126.com>
License: This package is proprietary and confidential.
Project-URL: Github, https://github.com/GchlDev/ThreatWeaver
Classifier: Programming Language :: Python :: 3
Requires-Python: >=3.8
License-File: LICENSE
Requires-Dist: graphviz==0.20.3
Requires-Dist: networkx==3.4.2
Requires-Dist: PyYAML==6.0.2
Dynamic: license-file
